{
	"info": {
		"_postman_id": "9c970afd-fa30-4576-a7fd-1a91b6c08226",
		"name": "Cheeky",
		"schema": "https://schema.getpostman.com/json/collection/v2.1.0/collection.json"
	},
	"item": [
		{
			"name": "User",
			"item": [
				{
					"name": "get all users",
					"protocolProfileBehavior": {
						"disableBodyPruning": true
					},
					"request": {
						"method": "GET",
						"header": [],
						"body": {
							"mode": "raw",
							"raw": "",
							"options": {
								"raw": {
									"language": "json"
								}
							}
						},
						"url": {
							"raw": "http://localhost:4000/api/user/",
							"protocol": "http",
							"host": [
								"localhost"
							],
							"port": "4000",
							"path": [
								"api",
								"user",
								""
							]
						}
					},
					"response": [
						{
							"name": "get all users",
							"originalRequest": {
								"method": "GET",
								"header": [],
								"body": {
									"mode": "raw",
									"raw": "",
									"options": {
										"raw": {
											"language": "json"
										}
									}
								},
								"url": {
									"raw": "http://localhost:4000/api/user/",
									"protocol": "http",
									"host": [
										"localhost"
									],
									"port": "4000",
									"path": [
										"api",
										"user",
										""
									]
								}
							},
							"_postman_previewlanguage": null,
							"header": null,
							"cookie": [],
							"body": null
						}
					]
				},
				{
					"name": "login user",
					"request": {
						"method": "POST",
						"header": [],
						"body": {
							"mode": "raw",
							"raw": "{\n    \"email\":\"willy@gmail.com\",\n    \"password\":\"azertyui\"\n}",
							"options": {
								"raw": {
									"language": "json"
								}
							}
						},
						"url": {
							"raw": "http://localhost:4000/api/user/login",
							"protocol": "http",
							"host": [
								"localhost"
							],
							"port": "4000",
							"path": [
								"api",
								"user",
								"login"
							]
						}
					},
					"response": [
						{
							"name": "login user",
							"originalRequest": {
								"method": "POST",
								"header": [],
								"body": {
									"mode": "raw",
									"raw": "{\n    \"email\":\"willy@gmail.com\",\n    \"password\":\"azertyui\"\n}",
									"options": {
										"raw": {
											"language": "json"
										}
									}
								},
								"url": {
									"raw": "http://localhost:4000/api/user/login",
									"protocol": "http",
									"host": [
										"localhost"
									],
									"port": "4000",
									"path": [
										"api",
										"user",
										"login"
									]
								}
							},
							"_postman_previewlanguage": null,
							"header": null,
							"cookie": [],
							"body": null
						}
					]
				},
				{
					"name": "register user",
					"request": {
						"method": "POST",
						"header": [],
						"body": {
							"mode": "raw",
							"raw": "{\n    \"pseudo\": \"smail\",\n    \"email\":\"smail@gmail.com\",\n    \"password\":\"azertyui\"\n}",
							"options": {
								"raw": {
									"language": "json"
								}
							}
						},
						"url": {
							"raw": "http://localhost:4000/api/user/register",
							"protocol": "http",
							"host": [
								"localhost"
							],
							"port": "4000",
							"path": [
								"api",
								"user",
								"register"
							]
						}
					},
					"response": [
						{
							"name": "register user",
							"originalRequest": {
								"method": "POST",
								"header": [],
								"body": {
									"mode": "raw",
									"raw": "{\n    \"pseudo\": \"smail\",\n    \"email\":\"smail@gmail.com\",\n    \"password\":\"azertyui\"\n}",
									"options": {
										"raw": {
											"language": "json"
										}
									}
								},
								"url": {
									"raw": "http://localhost:4000/api/user/register",
									"protocol": "http",
									"host": [
										"localhost"
									],
									"port": "4000",
									"path": [
										"api",
										"user",
										"register"
									]
								}
							},
							"_postman_previewlanguage": null,
							"header": null,
							"cookie": [],
							"body": null
						}
					]
				},
				{
					"name": "user info",
					"protocolProfileBehavior": {
						"disableBodyPruning": true
					},
					"request": {
						"method": "GET",
						"header": [],
						"body": {
							"mode": "raw",
							"raw": "",
							"options": {
								"raw": {
									"language": "json"
								}
							}
						},
						"url": {
							"raw": "http://localhost:4000/api/user/62446015a314d719cf52b392",
							"protocol": "http",
							"host": [
								"localhost"
							],
							"port": "4000",
							"path": [
								"api",
								"user",
								"62446015a314d719cf52b392"
							]
						}
					},
					"response": [
						{
							"name": "user info",
							"originalRequest": {
								"method": "GET",
								"header": [],
								"body": {
									"mode": "raw",
									"raw": "",
									"options": {
										"raw": {
											"language": "json"
										}
									}
								},
								"url": {
									"raw": "http://localhost:4000/api/user/62446015a314d719cf52b392",
									"protocol": "http",
									"host": [
										"localhost"
									],
									"port": "4000",
									"path": [
										"api",
										"user",
										"62446015a314d719cf52b392"
									]
								}
							},
							"_postman_previewlanguage": null,
							"header": null,
							"cookie": [],
							"body": null
						}
					]
				},
				{
					"name": "update user",
					"request": {
						"method": "PUT",
						"header": [],
						"body": {
							"mode": "raw",
							"raw": "{\n    \"bio\":\"J'aime le bleu\"\n}",
							"options": {
								"raw": {
									"language": "json"
								}
							}
						},
						"url": {
							"raw": "http://localhost:4000/api/user/62446015a314d719cf52b392",
							"protocol": "http",
							"host": [
								"localhost"
							],
							"port": "4000",
							"path": [
								"api",
								"user",
								"62446015a314d719cf52b392"
							]
						}
					},
					"response": [
						{
							"name": "update user",
							"originalRequest": {
								"method": "PUT",
								"header": [],
								"body": {
									"mode": "raw",
									"raw": "{\n    \"bio\":\"J'aime le bleu\"\n}",
									"options": {
										"raw": {
											"language": "json"
										}
									}
								},
								"url": {
									"raw": "http://localhost:4000/api/user/62446015a314d719cf52b392",
									"protocol": "http",
									"host": [
										"localhost"
									],
									"port": "4000",
									"path": [
										"api",
										"user",
										"62446015a314d719cf52b392"
									]
								}
							},
							"_postman_previewlanguage": null,
							"header": null,
							"cookie": [],
							"body": null
						}
					]
				},
				{
					"name": "upload picture",
					"request": {
						"method": "POST",
						"header": [],
						"body": {
							"mode": "formdata",
							"formdata": [
								{
									"key": "file",
									"type": "file",
									"src": "/Users/ihsaneboubrik/Pictures/Photos Library.photoslibrary/originals/4/410AE1C9-2E13-4226-8B17-C04ACADAFD1C.jpeg"
								},
								{
									"key": "name",
									"value": "dannyv",
									"type": "default"
								},
								{
									"key": "userId",
									"value": "6272f7c1ed114b6218b9707d",
									"type": "default"
								}
							],
							"options": {
								"raw": {
									"language": "json"
								}
							}
						},
						"url": {
							"raw": "http://localhost:4000/api/user/upload/",
							"protocol": "http",
							"host": [
								"localhost"
							],
							"port": "4000",
							"path": [
								"api",
								"user",
								"upload",
								""
							]
						}
					},
					"response": [
						{
							"name": "upload picture",
							"originalRequest": {
								"method": "POST",
								"header": [],
								"body": {
									"mode": "formdata",
									"formdata": [
										{
											"key": "file",
											"type": "file",
											"src": "/Users/ihsaneboubrik/Pictures/Photos Library.photoslibrary/originals/4/410AE1C9-2E13-4226-8B17-C04ACADAFD1C.jpeg"
										},
										{
											"key": "name",
											"value": "dannyv",
											"type": "default"
										},
										{
											"key": "userId",
											"value": "6272f7c1ed114b6218b9707d",
											"type": "default"
										}
									],
									"options": {
										"raw": {
											"language": "json"
										}
									}
								},
								"url": {
									"raw": "http://localhost:4000/api/user/upload/",
									"protocol": "http",
									"host": [
										"localhost"
									],
									"port": "4000",
									"path": [
										"api",
										"user",
										"upload",
										""
									]
								}
							},
							"_postman_previewlanguage": null,
							"header": null,
							"cookie": [],
							"body": null
						}
					]
				},
				{
					"name": "delete user",
					"request": {
						"method": "DELETE",
						"header": [],
						"body": {
							"mode": "raw",
							"raw": "",
							"options": {
								"raw": {
									"language": "json"
								}
							}
						},
						"url": {
							"raw": "http://localhost:4000/api/user/6272f19f788a806171a4198c",
							"protocol": "http",
							"host": [
								"localhost"
							],
							"port": "4000",
							"path": [
								"api",
								"user",
								"6272f19f788a806171a4198c"
							]
						}
					},
					"response": [
						{
							"name": "delete user",
							"originalRequest": {
								"method": "DELETE",
								"header": [],
								"body": {
									"mode": "raw",
									"raw": "",
									"options": {
										"raw": {
											"language": "json"
										}
									}
								},
								"url": {
									"raw": "http://localhost:4000/api/user/6272f19f788a806171a4198c",
									"protocol": "http",
									"host": [
										"localhost"
									],
									"port": "4000",
									"path": [
										"api",
										"user",
										"6272f19f788a806171a4198c"
									]
								}
							},
							"_postman_previewlanguage": null,
							"header": null,
							"cookie": [],
							"body": null
						}
					]
				}
			]
		},
		{
			"name": "Post",
			"item": [
				{
					"name": "get all posts",
					"request": {
						"method": "GET",
						"header": [],
						"url": {
							"raw": "http://localhost:4000/api/post/",
							"protocol": "http",
							"host": [
								"localhost"
							],
							"port": "4000",
							"path": [
								"api",
								"post",
								""
							]
						}
					},
					"response": [
						{
							"name": "get all posts",
							"originalRequest": {
								"method": "GET",
								"header": [],
								"url": {
									"raw": "http://localhost:4000/api/post/",
									"protocol": "http",
									"host": [
										"localhost"
									],
									"port": "4000",
									"path": [
										"api",
										"post",
										""
									]
								}
							},
							"_postman_previewlanguage": null,
							"header": null,
							"cookie": [],
							"body": null
						}
					]
				},
				{
					"name": "add post",
					"request": {
						"method": "POST",
						"header": [],
						"body": {
							"mode": "raw",
							"raw": "{\n    \"posterId\":\"62446059a314d719cf52b39d\",\n    \"message\":\"hello\"\n}",
							"options": {
								"raw": {
									"language": "json"
								}
							}
						},
						"url": {
							"raw": "http://localhost:4000/api/post/",
							"protocol": "http",
							"host": [
								"localhost"
							],
							"port": "4000",
							"path": [
								"api",
								"post",
								""
							]
						}
					},
					"response": [
						{
							"name": "add post",
							"originalRequest": {
								"method": "POST",
								"header": [],
								"body": {
									"mode": "raw",
									"raw": "{\n    \"posterId\":\"62446059a314d719cf52b39d\",\n    \"message\":\"hello\"\n}",
									"options": {
										"raw": {
											"language": "json"
										}
									}
								},
								"url": {
									"raw": "http://localhost:4000/api/post/",
									"protocol": "http",
									"host": [
										"localhost"
									],
									"port": "4000",
									"path": [
										"api",
										"post",
										""
									]
								}
							},
							"_postman_previewlanguage": null,
							"header": null,
							"cookie": [],
							"body": null
						}
					]
				},
				{
					"name": "like post",
					"request": {
						"method": "PATCH",
						"header": [],
						"body": {
							"mode": "raw",
							"raw": "{\n    \"id\":\"62446059a314d719cf52b39d\"\n}",
							"options": {
								"raw": {
									"language": "json"
								}
							}
						},
						"url": {
							"raw": "http://localhost:4000/api/post/like-post/625ebd84e64d463128b21581",
							"protocol": "http",
							"host": [
								"localhost"
							],
							"port": "4000",
							"path": [
								"api",
								"post",
								"like-post",
								"625ebd84e64d463128b21581"
							]
						}
					},
					"response": [
						{
							"name": "like post",
							"originalRequest": {
								"method": "PATCH",
								"header": [],
								"body": {
									"mode": "raw",
									"raw": "{\n    \"id\":\"62446059a314d719cf52b39d\"\n}",
									"options": {
										"raw": {
											"language": "json"
										}
									}
								},
								"url": {
									"raw": "http://localhost:4000/api/post/like-post/625ebd84e64d463128b21581",
									"protocol": "http",
									"host": [
										"localhost"
									],
									"port": "4000",
									"path": [
										"api",
										"post",
										"like-post",
										"625ebd84e64d463128b21581"
									]
								}
							},
							"_postman_previewlanguage": null,
							"header": null,
							"cookie": [],
							"body": null
						}
					]
				},
				{
					"name": "unlike post",
					"request": {
						"method": "PATCH",
						"header": [],
						"body": {
							"mode": "raw",
							"raw": "{\n    \"id\":\"62446059a314d719cf52b39d\"\n}",
							"options": {
								"raw": {
									"language": "json"
								}
							}
						},
						"url": {
							"raw": "http://localhost:4000/api/post/unlike-post/625ebd84e64d463128b21581",
							"protocol": "http",
							"host": [
								"localhost"
							],
							"port": "4000",
							"path": [
								"api",
								"post",
								"unlike-post",
								"625ebd84e64d463128b21581"
							]
						}
					},
					"response": [
						{
							"name": "unlike post",
							"originalRequest": {
								"method": "PATCH",
								"header": [],
								"body": {
									"mode": "raw",
									"raw": "{\n    \"id\":\"62446059a314d719cf52b39d\"\n}",
									"options": {
										"raw": {
											"language": "json"
										}
									}
								},
								"url": {
									"raw": "http://localhost:4000/api/post/unlike-post/625ebd84e64d463128b21581",
									"protocol": "http",
									"host": [
										"localhost"
									],
									"port": "4000",
									"path": [
										"api",
										"post",
										"unlike-post",
										"625ebd84e64d463128b21581"
									]
								}
							},
							"_postman_previewlanguage": null,
							"header": null,
							"cookie": [],
							"body": null
						}
					]
				},
				{
					"name": "udate post",
					"request": {
						"method": "PUT",
						"header": [],
						"body": {
							"mode": "raw",
							"raw": "{\n    \"message\":\"hol\"\n}",
							"options": {
								"raw": {
									"language": "json"
								}
							}
						},
						"url": {
							"raw": "http://localhost:4000/api/post/6272ea7b4a66f26083e13ed2",
							"protocol": "http",
							"host": [
								"localhost"
							],
							"port": "4000",
							"path": [
								"api",
								"post",
								"6272ea7b4a66f26083e13ed2"
							]
						}
					},
					"response": [
						{
							"name": "udate post",
							"originalRequest": {
								"method": "PUT",
								"header": [],
								"body": {
									"mode": "raw",
									"raw": "{\n    \"message\":\"hol\"\n}",
									"options": {
										"raw": {
											"language": "json"
										}
									}
								},
								"url": {
									"raw": "http://localhost:4000/api/post/6272ea7b4a66f26083e13ed2",
									"protocol": "http",
									"host": [
										"localhost"
									],
									"port": "4000",
									"path": [
										"api",
										"post",
										"6272ea7b4a66f26083e13ed2"
									]
								}
							},
							"_postman_previewlanguage": null,
							"header": null,
							"cookie": [],
							"body": null
						}
					]
				},
				{
					"name": "delete post",
					"request": {
						"method": "DELETE",
						"header": [],
						"url": {
							"raw": "http://localhost:4000/api/post/6272ea7b4a66f26083e13ed2",
							"protocol": "http",
							"host": [
								"localhost"
							],
							"port": "4000",
							"path": [
								"api",
								"post",
								"6272ea7b4a66f26083e13ed2"
							]
						}
					},
					"response": [
						{
							"name": "delete post",
							"originalRequest": {
								"method": "DELETE",
								"header": [],
								"url": {
									"raw": "http://localhost:4000/api/post/6272ea7b4a66f26083e13ed2",
									"protocol": "http",
									"host": [
										"localhost"
									],
									"port": "4000",
									"path": [
										"api",
										"post",
										"6272ea7b4a66f26083e13ed2"
									]
								}
							},
							"_postman_previewlanguage": null,
							"header": null,
							"cookie": [],
							"body": null
						}
					]
				},
				{
					"name": "comment post",
					"request": {
						"method": "PATCH",
						"header": [],
						"body": {
							"mode": "raw",
							"raw": "{\n    \"commenterId\": \"62446015a314d719cf52b392\",\n\t\"commenterPseudo\": \"ouilly\",\n    \"text\": \"waw\"\n}",
							"options": {
								"raw": {
									"language": "json"
								}
							}
						},
						"url": {
							"raw": "http://localhost:4000/api/post/comment-post/6272ee0e4a66f26083e13eed",
							"protocol": "http",
							"host": [
								"localhost"
							],
							"port": "4000",
							"path": [
								"api",
								"post",
								"comment-post",
								"6272ee0e4a66f26083e13eed"
							]
						}
					},
					"response": [
						{
							"name": "comment post",
							"originalRequest": {
								"method": "PATCH",
								"header": [],
								"body": {
									"mode": "raw",
									"raw": "{\n    \"commenterId\": \"62446015a314d719cf52b392\",\n\t\"commenterPseudo\": \"ouilly\",\n    \"text\": \"waw\"\n}",
									"options": {
										"raw": {
											"language": "json"
										}
									}
								},
								"url": {
									"raw": "http://localhost:4000/api/post/comment-post/6272ee0e4a66f26083e13eed",
									"protocol": "http",
									"host": [
										"localhost"
									],
									"port": "4000",
									"path": [
										"api",
										"post",
										"comment-post",
										"6272ee0e4a66f26083e13eed"
									]
								}
							},
							"_postman_previewlanguage": null,
							"header": null,
							"cookie": [],
							"body": null
						}
					]
				},
				{
					"name": "edit comment ",
					"request": {
						"method": "PATCH",
						"header": [],
						"body": {
							"mode": "raw",
							"raw": "{\n    \"commentId\": \"6272efa54a66f26083e13ef7\",\n    \"text\": \"incroyable\"\n}",
							"options": {
								"raw": {
									"language": "json"
								}
							}
						},
						"url": {
							"raw": "http://localhost:4000/api/post/edit-comment-post/6272ee0e4a66f26083e13eed",
							"protocol": "http",
							"host": [
								"localhost"
							],
							"port": "4000",
							"path": [
								"api",
								"post",
								"edit-comment-post",
								"6272ee0e4a66f26083e13eed"
							]
						}
					},
					"response": [
						{
							"name": "edit comment ",
							"originalRequest": {
								"method": "PATCH",
								"header": [],
								"body": {
									"mode": "raw",
									"raw": "{\n    \"commentId\": \"6272efa54a66f26083e13ef7\",\n    \"text\": \"incroyable\"\n}",
									"options": {
										"raw": {
											"language": "json"
										}
									}
								},
								"url": {
									"raw": "http://localhost:4000/api/post/edit-comment-post/6272ee0e4a66f26083e13eed",
									"protocol": "http",
									"host": [
										"localhost"
									],
									"port": "4000",
									"path": [
										"api",
										"post",
										"edit-comment-post",
										"6272ee0e4a66f26083e13eed"
									]
								}
							},
							"_postman_previewlanguage": null,
							"header": null,
							"cookie": [],
							"body": null
						}
					]
				},
				{
					"name": "delete comment ",
					"request": {
						"method": "PATCH",
						"header": [],
						"body": {
							"mode": "raw",
							"raw": "{\n    \"commentId\": \"6272efa54a66f26083e13ef7\"\n}",
							"options": {
								"raw": {
									"language": "json"
								}
							}
						},
						"url": {
							"raw": "http://localhost:4000/api/post/delete-comment-post/6272ee0e4a66f26083e13eed",
							"protocol": "http",
							"host": [
								"localhost"
							],
							"port": "4000",
							"path": [
								"api",
								"post",
								"delete-comment-post",
								"6272ee0e4a66f26083e13eed"
							]
						}
					},
					"response": [
						{
							"name": "delete comment ",
							"originalRequest": {
								"method": "PATCH",
								"header": [],
								"body": {
									"mode": "raw",
									"raw": "{\n    \"commentId\": \"6272efa54a66f26083e13ef7\"\n}",
									"options": {
										"raw": {
											"language": "json"
										}
									}
								},
								"url": {
									"raw": "http://localhost:4000/api/post/delete-comment-post/6272ee0e4a66f26083e13eed",
									"protocol": "http",
									"host": [
										"localhost"
									],
									"port": "4000",
									"path": [
										"api",
										"post",
										"delete-comment-post",
										"6272ee0e4a66f26083e13eed"
									]
								}
							},
							"_postman_previewlanguage": null,
							"header": null,
							"cookie": [],
							"body": null
						}
					]
				}
			]
		},
		{
			"name": "Friend",
			"item": [
				{
					"name": "follow user",
					"request": {
						"method": "PATCH",
						"header": [],
						"body": {
							"mode": "raw",
							"raw": "{\n    \"idToFollow\":\"6272f7c1ed114b6218b9707d\"\n}",
							"options": {
								"raw": {
									"language": "json"
								}
							}
						},
						"url": {
							"raw": "http://localhost:4000/api/user/follow/62446015a314d719cf52b392",
							"protocol": "http",
							"host": [
								"localhost"
							],
							"port": "4000",
							"path": [
								"api",
								"user",
								"follow",
								"62446015a314d719cf52b392"
							]
						}
					},
					"response": [
						{
							"name": "follow user",
							"originalRequest": {
								"method": "PATCH",
								"header": [],
								"body": {
									"mode": "raw",
									"raw": "{\n    \"idToFollow\":\"6272f7c1ed114b6218b9707d\"\n}",
									"options": {
										"raw": {
											"language": "json"
										}
									}
								},
								"url": {
									"raw": "http://localhost:4000/api/user/follow/62446015a314d719cf52b392",
									"protocol": "http",
									"host": [
										"localhost"
									],
									"port": "4000",
									"path": [
										"api",
										"user",
										"follow",
										"62446015a314d719cf52b392"
									]
								}
							},
							"_postman_previewlanguage": null,
							"header": null,
							"cookie": [],
							"body": null
						}
					]
				},
				{
					"name": "unfollow user",
					"request": {
						"method": "PATCH",
						"header": [],
						"body": {
							"mode": "raw",
							"raw": "{\n    \"idToUnFollow\":\"6272f7c1ed114b6218b9707d\"\n}",
							"options": {
								"raw": {
									"language": "json"
								}
							}
						},
						"url": {
							"raw": "http://localhost:4000/api/user/unfollow/62446015a314d719cf52b392",
							"protocol": "http",
							"host": [
								"localhost"
							],
							"port": "4000",
							"path": [
								"api",
								"user",
								"unfollow",
								"62446015a314d719cf52b392"
							]
						}
					},
					"response": [
						{
							"name": "unfollow user",
							"originalRequest": {
								"method": "PATCH",
								"header": [],
								"body": {
									"mode": "raw",
									"raw": "{\n    \"idToUnFollow\":\"6272f7c1ed114b6218b9707d\"\n}",
									"options": {
										"raw": {
											"language": "json"
										}
									}
								},
								"url": {
									"raw": "http://localhost:4000/api/user/unfollow/62446015a314d719cf52b392",
									"protocol": "http",
									"host": [
										"localhost"
									],
									"port": "4000",
									"path": [
										"api",
										"user",
										"unfollow",
										"62446015a314d719cf52b392"
									]
								}
							},
							"_postman_previewlanguage": null,
							"header": null,
							"cookie": [],
							"body": null
						}
					]
				}
			]
		}
	]
}